{"level_id":2,"level_time":60,"world_center_x":0,"world_center_y":0,"rope_structure":[{"jammer":{"global_index":12,"position":{"x":3.4996891021728517,"y":2.2720513343811037},"angle":-1.7012566328048707,"type":2,"fixture":[{"circle":{"center":0,"radius":0.4},"friction":0.2,"restitution":0.1}]},"rope":[[{"global_index":6,"local_index":0,"position":{"x":-3.5,"y":-2.5},"angle":1.2683738470077515,"type":2,"fixture":[{"density":1,"friction":0.2,"polygon":{"vertices":{"x":[0.1,0.1,-0.1,-0.1],"y":[-0.2,0.2,0.2,-0.2]}}}]},{"global_index":11,"local_index":1,"position":{"x":-3.5,"y":-2.5},"angle":1.2036675214767457,"type":2,"fixture":[{"density":1,"friction":0.2,"polygon":{"vertices":{"x":[0.1,0.1,-0.1,-0.1],"y":[-0.2,0.2,0.2,-0.2]}}}]},{"global_index":4,"local_index":2,"position":{"x":-3.5,"y":-2.5},"angle":1.20682954788208,"type":2,"fixture":[{"density":1,"friction":0.2,"polygon":{"vertices":{"x":[0.1,0.1,-0.1,-0.1],"y":[-0.2,0.2,0.2,-0.2]}}}]},{"global_index":8,"local_index":3,"position":{"x":-3.5,"y":-2.5},"angle":1.2169411182403565,"type":2,"fixture":[{"density":1,"friction":0.2,"polygon":{"vertices":{"x":[0.1,0.1,-0.1,-0.1],"y":[-0.2,0.2,0.2,-0.2]}}}]},{"global_index":3,"local_index":4,"position":{"x":-3.5,"y":-2.5},"angle":1.216066837310791,"type":2,"fixture":[{"density":1,"friction":0.2,"polygon":{"vertices":{"x":[0.1,0.1,-0.1,-0.1],"y":[-0.2,0.2,0.2,-0.2]}}}]}],[{"global_index":13,"local_index":0,"position":{"x":-3.5,"y":-2.5},"angle":-7.614351749420166,"type":2,"fixture":[{"density":1,"friction":0.2,"polygon":{"vertices":{"x":[0.1,0.1,-0.1,-0.1],"y":[-0.2,0.2,0.2,-0.2]}}}]},{"global_index":9,"local_index":1,"position":{"x":-3.5,"y":-2.5},"angle":-7.5207648277282719,"type":2,"fixture":[{"density":1,"friction":0.2,"polygon":{"vertices":{"x":[0.1,0.1,-0.1,-0.1],"y":[-0.2,0.2,0.2,-0.2]}}}]},{"global_index":10,"local_index":2,"position":{"x":-3.5,"y":-2.5},"angle":-1.2017695903778077,"type":2,"fixture":[{"density":1,"friction":0.2,"polygon":{"vertices":{"x":[0.1,0.1,-0.1,-0.1],"y":[-0.2,0.2,0.2,-0.2]}}}]},{"global_index":7,"local_index":3,"position":{"x":-3.5,"y":-2.5},"angle":-1.1752667427062989,"type":2,"fixture":[{"density":1,"friction":0.2,"polygon":{"vertices":{"x":[0.1,0.1,-0.1,-0.1],"y":[-0.2,0.2,0.2,-0.2]}}}]},{"global_index":14,"local_index":4,"position":{"x":-3.5,"y":-2.5},"angle":-1.1479078531265259,"type":2,"fixture":[{"density":1,"friction":0.2,"polygon":{"vertices":{"x":[0.1,0.1,-0.1,-0.1],"y":[-0.2,0.2,0.2,-0.2]}}}]}]],"hinge":[{"global_index":5,"position":{"x":1.5,"y":3.0},"angle":0.0,"type":0,"fixture":[{"circle":{"center":0,"radius":0.25},"density":1,"friction":0.2}]},{"global_index":15,"position":{"x":5.5,"y":3.0},"angle":0.0,"type":0,"fixture":[{"circle":{"center":0,"radius":0.25},"density":1,"friction":0.2}]}]}],"platform":[{"global_index":1,"position":{"x":-4.0,"y":-1.0},"angle":0.0,"type":0,"fixture":[{"chain":{"vertices":{"x":[-2,2],"y":[0.0,0.0]}},"density":1,"friction":0.2}]},{"global_index":2,"position":{"x":-4.0,"y":-3.0},"angle":0.0,"type":0,"fixture":[{"chain":{"vertices":{"x":[-2,2],"y":[0.0,0.0]}},"density":1,"friction":0.2}]}],"enemy":[{"global_index":0,"position":{"x":-3.5,"y":-2.5},"angle":0.00029586831806227565,"type":2,"fixture":[{"density":5,"friction":0.2,"restitution":0.1,"polygon":{"vertices":{"x":[0.45,0.45,-0.45,-0.45],"y":[-0.45,0.45,0.45,-0.45]}}}]}],"collectable":[],"joint":[{"anchorA":{"x":-5.4239094993135959e-8,"y":0.2},"anchorB":0,"bodyA":3,"bodyB":5,"enableLimit":false,"enableMotor":false,"jointSpeed":-0.5321439504623413,"lowerLimit":0,"maxMotorTorque":0,"motorSpeed":0,"name":"joint10","refAngle":0,"type":"revolute","upperLimit":0,"nameA":"structure_0_rope_0_4","nameB":"structure_0_hinge_0"},{"anchorA":{"x":-5.470171515753464e-8,"y":0.2},"anchorB":{"x":5.4239094993135959e-8,"y":-0.2},"bodyA":8,"bodyB":3,"enableLimit":false,"enableMotor":false,"jointSpeed":0.01847678422927856,"lowerLimit":0,"maxMotorTorque":0,"motorSpeed":0,"name":"joint5","refAngle":0,"type":"revolute","upperLimit":0,"nameA":"structure_0_rope_0_3","nameB":"structure_0_rope_0_4"},{"anchorA":{"x":1.282815560443851e-7,"y":0.2},"anchorB":0,"bodyA":14,"bodyB":15,"enableLimit":false,"enableMotor":false,"jointSpeed":-0.6181830763816834,"lowerLimit":0,"maxMotorTorque":0,"motorSpeed":0,"name":"joint11","refAngle":0,"type":"revolute","upperLimit":0,"nameA":"structure_0_rope_1_4","nameB":"structure_0_hinge_1"},{"anchorA":{"x":-4.618974713821444e-8,"y":0.2},"anchorB":{"x":-7.235944821104568e-8,"y":-0.2},"bodyA":13,"bodyB":9,"enableLimit":false,"enableMotor":false,"jointSpeed":2.546983242034912,"lowerLimit":0,"maxMotorTorque":0,"motorSpeed":0,"name":"joint6","refAngle":0,"type":"revolute","upperLimit":0,"nameA":"structure_0_rope_1_0","nameB":"structure_0_rope_1_1"},{"anchorA":{"x":-1.564828977507204e-8,"y":0.2},"anchorB":{"x":5.470171515753464e-8,"y":-0.2},"bodyA":4,"bodyB":8,"enableLimit":false,"enableMotor":false,"jointSpeed":0.2745055854320526,"lowerLimit":0,"maxMotorTorque":0,"motorSpeed":0,"name":"joint4","refAngle":0,"type":"revolute","upperLimit":0,"nameA":"structure_0_rope_0_2","nameB":"structure_0_rope_0_3"},{"anchorA":{"x":4.333401193434838e-8,"y":0.2},"anchorB":{"x":8.43003320483149e-8,"y":-0.2},"bodyA":6,"bodyB":11,"enableLimit":false,"enableMotor":false,"jointSpeed":-0.2491071224212647,"lowerLimit":0,"maxMotorTorque":0,"motorSpeed":0,"name":"joint2","refAngle":0,"type":"revolute","upperLimit":0,"nameA":"structure_0_rope_0_0","nameB":"structure_0_rope_0_1"},{"anchorA":0,"anchorB":{"x":-4.333401193434838e-8,"y":-0.2},"bodyA":12,"bodyB":6,"enableLimit":false,"enableMotor":false,"jointSpeed":-1.208250164985657,"lowerLimit":0,"maxMotorTorque":0,"motorSpeed":0,"name":"joint0","refAngle":0,"type":"revolute","upperLimit":0,"nameA":"structure_0_jammer","nameB":"structure_0_rope_0_0"},{"anchorA":{"x":-1.651226284593577e-7,"y":0.2},"anchorB":{"x":-1.282815560443851e-7,"y":-0.2},"bodyA":7,"bodyB":14,"enableLimit":false,"enableMotor":false,"jointSpeed":0.7567327618598938,"lowerLimit":0,"maxMotorTorque":0,"motorSpeed":0,"name":"joint9","refAngle":0,"type":"revolute","upperLimit":0,"nameA":"structure_0_rope_1_3","nameB":"structure_0_rope_1_4"},{"anchorA":{"x":-5.0769727977240118e-8,"y":0.2},"anchorB":{"x":1.651226284593577e-7,"y":-0.2},"bodyA":10,"bodyB":7,"enableLimit":false,"enableMotor":false,"jointSpeed":-0.3187663555145264,"lowerLimit":0,"maxMotorTorque":0,"motorSpeed":0,"name":"joint8","refAngle":0,"type":"revolute","upperLimit":0,"nameA":"structure_0_rope_1_2","nameB":"structure_0_rope_1_3"},{"anchorA":{"x":1.503424869042647e-7,"y":0.2},"anchorB":{"x":5.0769727977240118e-8,"y":-0.2},"bodyA":9,"bodyB":10,"enableLimit":false,"enableMotor":false,"jointSpeed":-1.682570576667786,"lowerLimit":0,"maxMotorTorque":0,"motorSpeed":0,"name":"joint7","refAngle":0,"type":"revolute","upperLimit":0,"nameA":"structure_0_rope_1_1","nameB":"structure_0_rope_1_2"},{"anchorA":{"x":-8.43003320483149e-8,"y":0.2},"anchorB":{"x":1.564828977507204e-8,"y":-0.2},"bodyA":11,"bodyB":4,"enableLimit":false,"enableMotor":false,"jointSpeed":1.866645812988281,"lowerLimit":0,"maxMotorTorque":0,"motorSpeed":0,"name":"joint3","refAngle":0,"type":"revolute","upperLimit":0,"nameA":"structure_0_rope_0_1","nameB":"structure_0_rope_0_2"},{"anchorA":0,"anchorB":{"x":4.618974713821444e-8,"y":-0.2},"bodyA":12,"bodyB":13,"enableLimit":false,"enableMotor":false,"jointSpeed":-0.5140689611434937,"lowerLimit":0,"maxMotorTorque":0,"motorSpeed":0,"name":"joint1","refAngle":0,"type":"revolute","upperLimit":0,"nameA":"structure_0_jammer","nameB":"structure_0_rope_1_0"}]}